LICENSE.txt
README.md
setup.cfg
setup.py
cvgui/__init__.py
cvgui.egg-info/PKG-INFO
cvgui.egg-info/SOURCES.txt
cvgui.egg-info/dependency_links.txt
cvgui.egg-info/requires.txt
cvgui.egg-info/top_level.txt
cvgui/activity/__init__.py
cvgui/activity/activity.py
cvgui/activity/scene.py
cvgui/core/__init__.py
cvgui/core/displaying/__init__.py
cvgui/core/displaying/components.py
cvgui/core/displaying/service.py
cvgui/core/logging/__init__.py
cvgui/core/logging/service.py
cvgui/core/receiving/__init__.py
cvgui/core/receiving/service.py
cvgui/inputs/__init__.py
cvgui/inputs/computer_vision/__init__.py
cvgui/inputs/computer_vision/computer_vision.py
cvgui/inputs/computer_vision/cv_model/__init__.py
cvgui/inputs/computer_vision/cv_model/blazepose.py
cvgui/inputs/computer_vision/frame_input/__init__.py
cvgui/inputs/computer_vision/frame_input/webcam.py
cvgui/outputs/__init__.py
cvgui/outputs/loggers/__init__.py
cvgui/outputs/loggers/csv_logger.py
cvgui/user_interface/__init__.py
cvgui/user_interface/pygame_ui/__init__.py
cvgui/user_interface/pygame_ui/pygame.py