Metadata-Version: 2.1
Name: cvgui
Version: 0.3.1
Summary: A library for creating body-interactive guis using computer vision.
Home-page: https://github.com/mitchellss/cvgui
Author: Stephen Mitchell
Author-email: stephen.mitchell2299@gmail.com
License: MIT
Requires-Python: >=3.9
License-File: LICENSE.txt
